paymentus_xotp/__init__.py
paymentus_xotp/api_client.py
paymentus_xotp/api_response.py
paymentus_xotp/configuration.py
paymentus_xotp/exceptions.py
paymentus_xotp/py.typed
paymentus_xotp/rest.py
paymentus_xotp/version.py
paymentus_xotp/api/__init__.py
paymentus_xotp/api/xotp_api.py
paymentus_xotp/client/__init__.py
paymentus_xotp/client/xotp_api_client.py
paymentus_xotp/logging/__init__.py
paymentus_xotp/middlewares/__init__.py
paymentus_xotp/middlewares/logging_middleware.py
paymentus_xotp/middlewares/response_normalizer.py
paymentus_xotp/models/__init__.py
paymentus_xotp/models/account_inquiry_detail.py
paymentus_xotp/models/account_inquiry_item.py
paymentus_xotp/models/account_inquiry_request.py
paymentus_xotp/models/account_inquiry_response.py
paymentus_xotp/models/address.py
paymentus_xotp/models/autopay_details.py
paymentus_xotp/models/autopay_failed_item.py
paymentus_xotp/models/autopay_failed_response.py
paymentus_xotp/models/autopay_find_response.py
paymentus_xotp/models/autopay_list_response.py
paymentus_xotp/models/autopay_list_response_item.py
paymentus_xotp/models/autopay_request.py
paymentus_xotp/models/autopay_request_item.py
paymentus_xotp/models/autopay_response.py
paymentus_xotp/models/autopay_response_header.py
paymentus_xotp/models/autopay_response_item.py
paymentus_xotp/models/autopay_response_payment_method.py
paymentus_xotp/models/autopay_response_schedule.py
paymentus_xotp/models/autopay_search_request.py
paymentus_xotp/models/bank_info_failed_item.py
paymentus_xotp/models/bank_info_failed_response.py
paymentus_xotp/models/bank_info_response.py
paymentus_xotp/models/bank_info_response_item.py
paymentus_xotp/models/calculate_cnv_fee.py
paymentus_xotp/models/calculate_cnv_fee_item.py
paymentus_xotp/models/client_account_item.py
paymentus_xotp/models/cnv_fee_config.py
paymentus_xotp/models/cnv_fee_response.py
paymentus_xotp/models/cnv_fee_response_item.py
paymentus_xotp/models/convenience_fee_category_code_enum.py
paymentus_xotp-1.0.4.dist-info/METADATA
paymentus_xotp-1.0.4.dist-info/WHEEL
paymentus_xotp-1.0.4.dist-info/top_level.txt
paymentus_xotp-1.0.4.dist-info/RECORD
