Metadata-Version: 2.4
Name: paymentus-xotp
Version: 1.0.4
Summary: Paymentus Python XOTP SDK
Author-email: Paymentus SDK Support <sdksupport@paymentus.com>
Maintainer-email: Paymentus SDK Support <sdksupport@paymentus.com>
License-Expression: MIT
Project-URL: Homepage, https://www.paymentus.com/
Project-URL: Source, https://developer.paymentus.io/
Keywords: paymentus,xotp,payment,api,sdk,transaction
Requires-Python: >=3.9
Requires-Dist: pydantic>=2.0.0
Requires-Dist: requests>=2.31.0
Requires-Dist: urllib3>=2.0.0
Requires-Dist: python-dateutil>=2.8.0
Requires-Dist: typing-extensions>=4.0.0
Requires-Dist: PyYAML>=6.0.2
Provides-Extra: dev
Requires-Dist: pytest>=7.0.0; extra == "dev"
Requires-Dist: black>=22.0.0; extra == "dev"
Requires-Dist: flake8>=4.0.0; extra == "dev"
Requires-Dist: isort>=5.0.0; extra == "dev"
Requires-Dist: twine>=4.0.0; extra == "dev"
Requires-Dist: build>=0.8.0; extra == "dev"
Provides-Extra: codegen
Requires-Dist: openapi-generator-cli>=7.0.0; extra == "codegen"
